s3synchrony/__init__.py
s3synchrony/s3synchrony.py
s3synchrony/DataPlatforms/__init__.py
s3synchrony/DataPlatforms/baseconn.py
s3synchrony/DataPlatforms/s3conn.py
s3synchrony-0.1.2.dist-info/COPYING.txt
s3synchrony-0.1.2.dist-info/LICENSE.md
s3synchrony-0.1.2.dist-info/METADATA
s3synchrony-0.1.2.dist-info/WHEEL
s3synchrony-0.1.2.dist-info/top_level.txt
s3synchrony-0.1.2.dist-info/RECORD
