Metadata-Version: 2.1
Name: s3synchrony
Version: 0.1.2
Summary: This package provides a service for synchronizing file creations, deletions, and modifications across users on an AWS S3 prefix.
Home-page: https://github.com/SevanBrodjian/s3synchrony
Author: Sevan Brodjian
Author-email: sevanbro7@gmail.com
License: LICENSE.md
License-File: LICENSE.md
License-File: COPYING.txt
